{
  "freq": {
    ".": 1,
    "._": 1,
    "_": 30,
    "_a": 1,
    "_an": 1,
    "_b": 1,
    "_by": 1,
    "_d": 1,
    "_de": 1,
    "_e": 1,
    "_el": 1,
    "_f": 1,
    "_fr": 1,
    "_h": 1,
    "_he": 1,
    "_i": 1,
    "_is": 1,
    "_m": 1,
    "_mi": 1,
    "_o": 2,
    "_of": 2,
    "_r": 1,
    "_ra": 1,
    "_t": 3,
    "_th": 3,
    "_u": 1,
    "_ur": 1,
    "a": 6,
    "a_": 1,
    "ac": 1,
    "act": 1,
    "ad": 1,
    "adi": 1,
    "an": 2,
    "and": 1,
    "ani": 1,
    "ay": 1,
    "ay_": 1,
    "b": 1,
    "by": 1,
    "byp": 1,
    "c": 3,
    "ca": 1,
    "cay": 1,
    "ct": 2,
    "ct_": 1,
    "cti": 1,
    "d": 4,
    "d_": 1,
    "de": 1,
    "dec": 1,
    "di": 1,
    "dio": 1,
    "du": 1,
    "duc": 1,
    "e": 9,
    "e_": 3,
    "ec": 1,
    "eca": 1,
    "el": 2,
    "ele": 1,
    "eli": 1,
    "em": 1,
    "eme": 1,
    "en": 2,
    "enn": 1,
    "ent": 1,
    "f": 3,
    "f_": 2,
    "fr": 1,
    "fro": 1,
    "h": 4,
    "he": 3,
    "he_": 2,
    "hel": 1,
    "ho": 1,
    "hor": 1,
    "i": 8,
    "ia": 1,
    "ia_": 1,
    "il": 1,
    "ill": 1,
    "io": 1,
    "ioa": 1,
    "is": 1,
    "is_": 1,
    "iu": 3,
    "ium": 3,
    "iv": 1,
    "ive": 1,
    "l": 4,
    "le": 2,
    "lem": 1,
    "len": 1,
    "li": 1,
    "liu": 1,
    "ll": 1,
    "lle": 1,
    "m": 6,
    "m.": 1,
    "m._": 1,
    "m_": 3,
    "me": 1,
    "men": 1,
    "mi": 1,
    "mil": 1,
    "n": 5,
    "nd": 1,
    "nd_": 1,
    "ni": 2,
    "nia": 1,
    "niu": 1,
    "nn": 1,
    "nni": 1,
    "nt": 1,
    "nts": 1,
    "o": 6,
    "oa": 1,
    "oac": 1,
    "od": 1,
    "odu": 1,
    "of": 2,
    "of_": 2,
    "om": 1,
    "om_": 1,
    "or": 1,
    "ori": 1,
    "p": 1,
    "pr": 1,
    "pro": 1,
    "r": 5,
    "ra": 2,
    "rad": 1,
    "ran": 1,
    "ri": 1,
    "riu": 1,
    "ro": 2,
    "rod": 1,
    "rom": 1,
    "s": 2,
    "s_": 2,
    "t": 6,
    "t_": 1,
    "th": 3,
    "the": 2,
    "tho": 1,
    "ti": 1,
    "tiv": 1,
    "ts": 1,
    "ts_": 1,
    "u": 5,
    "uc": 1,
    "uct": 1,
    "um": 3,
    "um.": 1,
    "um_": 2,
    "ur": 1,
    "ura": 1,
    "v": 1,
    "ve": 1,
    "ve_": 1,
    "y": 2,
    "y_": 1,
    "yp": 1,
    "ypr": 1
  },
  "n_words": [
    21,
    71,
    73
  ],
  "name": "en",
  "probs": {
    ".": -4.718498871295094,
    "._": 0.0,
    "_": -1.3173014896329391,
    "_a": -2.70805020110221,
    "_an": 0.0,
    "_b": -2.70805020110221,
    "_by": 0.0,
    "_d": -2.70805020110221,
    "_de": 0.0,
    "_e": -2.70805020110221,
    "_el": 0.0,
    "_f": -2.70805020110221,
    "_fr": 0.0,
    "_h": -2.70805020110221,
    "_he": 0.0,
    "_i": -2.70805020110221,
    "_is": 0.0,
    "_m": -2.70805020110221,
    "_mi": 0.0,
    "_o": -2.0149030205422647,
    "_of": 0.0,
    "_r": -2.70805020110221,
    "_ra": 0.0,
    "_t": -1.6094379124341003,
    "_th": 0.0,
    "_u": -2.70805020110221,
    "_ur": 0.0,
    "a": -2.9267394020670396,
    "a_": -1.791759469228055,
    "ac": -1.791759469228055,
    "act": 0.0,
    "ad": -1.791759469228055,
    "adi": 0.0,
    "an": -1.0986122886681098,
    "and": -0.6931471805599453,
    "ani": -0.6931471805599453,
    "ay": -1.791759469228055,
    "ay_": 0.0,
    "b": -4.718498871295094,
    "by": 0.0,
    "byp": 0.0,
    "c": -3.619886582626985,
    "ca": -1.0986122886681098,
    "cay": 0.0,
    "ct": -0.40546510810816444,
    "ct_": -0.6931471805599453,
    "cti": -0.6931471805599453,
    "d": -3.332204510175204,
    "d_": -1.3862943611198906,
    "de": -1.3862943611198906,
    "dec": 0.0,
    "di": -1.3862943611198906,
    "dio": 0.0,
    "du": -1.3862943611198906,
    "duc": 0.0,
    "e": -2.521274293958875,
    "e_": -1.0986122886681098,
    "ec": -2.1972245773362196,
    "eca": 0.0,
    "el": -1.5040773967762742,
    "ele": -0.6931471805599453,
    "eli": -0.6931471805599453,
    "em": -2.1972245773362196,
    "eme": 0.0,
    "en": -1.5040773967762742,
    "enn": -0.6931471805599453,
    "ent": -0.6931471805599453,
    "f": -3.619886582626985,
    "f_": -0.40546510810816444,
    "fr": -1.0986122886681098,
    "fro": 0.0,
    "h": -3.332204510175204,
    "he": -0.2876820724517809,
    "he_": -0.40546510810816444,
    "hel": -1.0986122886681098,
    "ho": -1.3862943611198906,
    "hor": 0.0,
    "i": -2.639057329615259,
    "ia": -2.0794415416798357,
    "ia_": 0.0,
    "il": -2.0794415416798357,
    "ill": 0.0,
    "io": -2.0794415416798357,
    "ioa": 0.0,
    "is": -2.0794415416798357,
    "is_": 0.0,
    "iu": -0.9808292530117262,
    "ium": 0.0,
    "iv": -2.0794415416798357,
    "ive": 0.0,
    "l": -3.332204510175204,
    "le": -0.6931471805599453,
    "lem": -0.6931471805599453,
    "len": -0.6931471805599453,
    "li": -1.3862943611198906,
    "liu": 0.0,
    "ll": -1.3862943611198906,
    "lle": 0.0,
    "m": -2.9267394020670396,
    "m.": -1.791759469228055,
    "m._": 0.0,
    "m_": -0.6931471805599453,
    "me": -1.791759469228055,
    "men": 0.0,
    "mi": -1.791759469228055,
    "mil": 0.0,
    "n": -3.109060958860994,
    "nd": -1.6094379124341003,
    "nd_": 0.0,
    "ni": -0.916290731874155,
    "nia": -0.6931471805599453,
    "niu": -0.6931471805599453,
    "nn": -1.6094379124341003,
    "nni": 0.0,
    "nt": -1.6094379124341003,
    "nts": 0.0,
    "o": -2.9267394020670396,
    "oa": -1.791759469228055,
    "oac": 0.0,
    "od": -1.791759469228055,
    "odu": 0.0,
    "of": -1.0986122886681098,
    "of_": 0.0,
    "om": -1.791759469228055,
    "om_": 0.0,
    "or": -1.791759469228055,
    "ori": 0.0,
    "p": -4.718498871295094,
    "pr": 0.0,
    "pro": 0.0,
    "r": -3.109060958860994,
    "ra": -0.916290731874155,
    "rad": -0.6931471805599453,
    "ran": -0.6931471805599453,
    "ri": -1.6094379124341003,
    "riu": 0.0,
    "ro": -0.916290731874155,
    "rod": -0.6931471805599453,
    "rom": -0.6931471805599453,
    "s": -4.02535169073515,
    "s_": 0.0,
    "t": -2.9267394020670396,
    "t_": -1.791759469228055,
    "th": -0.6931471805599453,
    "the": -0.40546510810816444,
    "tho": -1.0986122886681098,
    "ti": -1.791759469228055,
    "tiv": 0.0,
    "ts": -1.791759469228055,
    "ts_": 0.0,
    "u": -3.109060958860994,
    "uc": -1.6094379124341003,
    "uct": 0.0,
    "um": -0.5108256237659907,
    "um.": -1.0986122886681098,
    "um_": -0.40546510810816444,
    "ur": -1.6094379124341003,
    "ura": 0.0,
    "v": -4.718498871295094,
    "ve": 0.0,
    "ve_": 0.0,
    "y": -4.02535169073515,
    "y_": -0.6931471805599453,
    "yp": -0.6931471805599453,
    "ypr": 0.0
  }
}